finstruments/__init__.py
finstruments/common/__init__.py
finstruments/common/base.py
finstruments/common/base_enum.py
finstruments/common/enum.py
finstruments/common/function.py
finstruments/common/period.py
finstruments/common/type.py
finstruments/common/date/__init__.py
finstruments/common/date/enum.py
finstruments/common/date/function.py
finstruments/common/decorators/__init__.py
finstruments/common/decorators/serializable/__init__.py
finstruments/common/decorators/serializable/__util.py
finstruments/common/decorators/serializable/decorators.py
finstruments/instrument/__init__.py
finstruments/instrument/abstract.py
finstruments/instrument/commodity/__init__.py
finstruments/instrument/commodity/instrument.py
finstruments/instrument/common/__init__.py
finstruments/instrument/common/cut.py
finstruments/instrument/common/enum.py
finstruments/instrument/common/exercise_style.py
finstruments/instrument/common/forward/__init__.py
finstruments/instrument/common/forward/instrument.py
finstruments/instrument/common/future/__init__.py
finstruments/instrument/common/future/instrument.py
finstruments/instrument/common/option/__init__.py
finstruments/instrument/common/option/enum.py
finstruments/instrument/common/option/instrument.py
finstruments/instrument/common/option/payoff.py
finstruments/instrument/equity/__init__.py
finstruments/instrument/equity/enum.py
finstruments/instrument/equity/instrument.py
finstruments/portfolio/__init__.py
finstruments/portfolio/portfolio.py
finstruments-1.0.6.dist-info/LICENSE
finstruments-1.0.6.dist-info/METADATA
finstruments-1.0.6.dist-info/WHEEL
finstruments-1.0.6.dist-info/top_level.txt
finstruments-1.0.6.dist-info/RECORD
