Metadata-Version: 2.1
Name: finstruments
Version: 1.0.6
Summary: Financial Instruments.
Home-page: https://kyleloomis.com/articles/financial-instrument-library
Author: Kyle Loomis
Author-email: kyle@spotlight.dev
Classifier: Programming Language :: Python :: 3
Classifier: Operating System :: OS Independent
Requires-Python: >=3.7
License-File: LICENSE
Requires-Dist: pydash >=7.0.3
Requires-Dist: pydantic ==1.10.17
Requires-Dist: pytz ==2024.2
Requires-Dist: workalendar ==17.0.0
Requires-Dist: python-dateutil ==2.9.0.post0
